{
	"separator_line_margin": {
		"prefix": "se",
		"body": ["________ $1"],
		"description": "sep_line_margin"
	},

	"separator_80": {
		"prefix": "se",
		"body": [
			"________________________________________________________________________________",
			"$1"
		],
		"description": "sep_80"
	},

	"separator_comment_multiline": {
		"prefix": "co",
		"body": [
			"/*******************************************************************************",
			"\n$1\n",
			"*******************************************************************************/"
		],
		"description": "comment_multiline"
	}
}
